roidynamics/__init__.py
roidynamics/splitmask.py
roidynamics/utils.py
roidynamics/tests/create_roi.ipynb
roidynamics/tests/test_splitmask.py
roidynamics/tests/test_folders/concentric_mask_w4_n3.tif
roidynamics/tests/test_folders/concentric_mask_w4_n3_b.tif
roidynamics/tests/test_folders/concentric_time.tif
roidynamics/tests/test_folders/test_multipage_good/C1-MAX_mitosis.tif
roidynamics/tests/test_folders/test_multipage_good/C2-MAX_mitosis.tif
roidynamics/tests/test_folders/test_multipage_good/multiroi.bmp
roidynamics/tests/test_folders/test_multipage_good/roi.bmp
roidynamics-0.2.0.dist-info/METADATA
roidynamics-0.2.0.dist-info/WHEEL
roidynamics-0.2.0.dist-info/licenses/LICENSE
roidynamics-0.2.0.dist-info/RECORD
