Metadata-Version: 2.1
Name: roidynamics
Version: 0.2.0
Summary: Time-evolution analysis of image intensity under specific mask geometries
Project-URL: homepage, https://github.com/guiwitz/roidynamics
Project-URL: repository, https://github.com/guiwitz/roidynamics
Author-email: Guillaume Witz <guillaume.witz@unibe.ch>
License: BSD 3-Clause License
License-File: LICENSE
Classifier: Development Status :: 3 - Alpha
Classifier: Intended Audience :: Education
Classifier: Intended Audience :: Science/Research
Classifier: License :: OSI Approved :: BSD License
Classifier: Natural Language :: English
Classifier: Operating System :: MacOS
Classifier: Operating System :: Microsoft :: Windows
Classifier: Operating System :: POSIX
Classifier: Operating System :: Unix
Classifier: Programming Language :: Python :: 3
Classifier: Programming Language :: Python :: 3.8
Classifier: Programming Language :: Python :: 3.9
Classifier: Programming Language :: Python :: 3.10
Classifier: Programming Language :: Python :: 3.11
Requires-Python: >=3.8
Requires-Dist: imageio
Requires-Dist: imageio-ffmpeg
Requires-Dist: matplotlib
Requires-Dist: microfilm[multipage]
Requires-Dist: numpy
Requires-Dist: pandas
Requires-Dist: scikit-image
Provides-Extra: interactive
Requires-Dist: ipywidgets; extra == 'interactive'
Requires-Dist: jupyterlab; extra == 'interactive'
Provides-Extra: test
Requires-Dist: pytest>=6.0; extra == 'test'
